tg_jarv_dialogue_manager/__init__.py
tg_jarv_dialogue_manager/py.typed
tg_jarv_dialogue_manager/db/chat_storage.py
tg_jarv_dialogue_manager/db/clickhouse_client.py
tg_jarv_dialogue_manager/services/jarv_client.py
tg_jarv_dialogue_manager/services/jarv_dialogue.py
tg_jarv_dialogue_manager-0.1.8.dist-info/licenses/LICENSE
tg_jarv_dialogue_manager-0.1.8.dist-info/METADATA
tg_jarv_dialogue_manager-0.1.8.dist-info/WHEEL
tg_jarv_dialogue_manager-0.1.8.dist-info/top_level.txt
tg_jarv_dialogue_manager-0.1.8.dist-info/RECORD
