Metadata-Version: 2.4
Name: tg-jarv-dialogue-manager
Version: 0.1.8
Summary: Jarv AI клиент и диалог-менеджер для Telegram с хранением истории в ClickHouse
Author: Александр Гаганов
License: MIT License
Project-URL: Homepage, https://pypi.org/project/tg-jarv-dialogue-manager/
Project-URL: Repository, https://github.com/GaganovAlexander/tg-jarv-dialogue-manager
Project-URL: Issues, https://github.com/GaganovAlexander/tg-jarv-dialogue-manager/issues
Keywords: jarv,telegram,clickhouse,dialogue,chat,asyncio,httpx
Classifier: Development Status :: 4 - Beta
Classifier: Intended Audience :: Developers
Classifier: License :: OSI Approved :: MIT License
Classifier: Programming Language :: Python :: 3
Classifier: Programming Language :: Python :: 3 :: Only
Classifier: Programming Language :: Python :: 3.10
Classifier: Programming Language :: Python :: 3.11
Classifier: Programming Language :: Python :: 3.12
Classifier: Topic :: Software Development :: Libraries
Classifier: Typing :: Typed
Requires-Python: >=3.10
License-File: LICENSE
Requires-Dist: httpx<1.0,>=0.24
Provides-Extra: telegram
Requires-Dist: python-telegram-bot>=21; extra == "telegram"
Dynamic: license-file
